stable_diffusion_pytorch/__init__.py
stable_diffusion_pytorch/attention.py
stable_diffusion_pytorch/clip.py
stable_diffusion_pytorch/decoder.py
stable_diffusion_pytorch/diffusion.py
stable_diffusion_pytorch/encoder.py
stable_diffusion_pytorch/model_loader.py
stable_diffusion_pytorch/pipeline.py
stable_diffusion_pytorch/tokenizer.py
stable_diffusion_pytorch/util.py
stable_diffusion_pytorch/samplers/__init__.py
stable_diffusion_pytorch/samplers/k_euler.py
stable_diffusion_pytorch/samplers/k_euler_ancestral.py
stable_diffusion_pytorch/samplers/k_lms.py
stable_diffusion_pytorch-0.0.6.dist-info/METADATA
stable_diffusion_pytorch-0.0.6.dist-info/WHEEL
stable_diffusion_pytorch-0.0.6.dist-info/top_level.txt
stable_diffusion_pytorch-0.0.6.dist-info/RECORD
