Metadata-Version: 2.1
Name: stable-diffusion-pytorch
Version: 0.0.6
Summary: stable-diffusion-pytorch
Author: Michiyasu Uchiyama
License: MIT
Keywords: stable diffusion
Classifier: License :: OSI Approved :: MIT License
Classifier: Programming Language :: Python :: 3.10
